LICENSE
MANIFEST.in
README.md
setup.py
Crondog_Client.egg-info/PKG-INFO
Crondog_Client.egg-info/SOURCES.txt
Crondog_Client.egg-info/dependency_links.txt
Crondog_Client.egg-info/entry_points.txt
Crondog_Client.egg-info/requires.txt
Crondog_Client.egg-info/top_level.txt
crondogclient/__init__.py
crondogclient/__main__.py
crondogclient/core.py
crondogclient/crondog.py