Metadata-Version: 1.0
Name: Crondog-Client
Version: 2.0.0dev3
Summary: Python command line client for crondog.
Home-page: http://hauntdigital.co.nz
Author: Craig Pearson
Author-email: admin@hauntdigital.co.nz
License: UNKNOWN
Platform: UNKNOWN
